sbtse/__init__.py
sbtse/_worm.py
sbtse/api.py
sbtse/errors.py
sbtse/main.py
sbtse/mockapi.py
sbtse/utils.py
sbtse/worm.py
sbtse-0.4.1.dist-info/LICENSE
sbtse-0.4.1.dist-info/METADATA
sbtse-0.4.1.dist-info/WHEEL
sbtse-0.4.1.dist-info/entry_points.txt
sbtse-0.4.1.dist-info/top_level.txt
sbtse-0.4.1.dist-info/RECORD
